torchtyping/__init__.py
torchtyping/pytest_plugin.py
torchtyping/tensor_details.py
torchtyping/tensor_type.py
torchtyping/typechecker.py
torchtyping/utils.py
torchtyping-0.1.5.dist-info/LICENSE
torchtyping-0.1.5.dist-info/METADATA
torchtyping-0.1.5.dist-info/WHEEL
torchtyping-0.1.5.dist-info/entry_points.txt
torchtyping-0.1.5.dist-info/top_level.txt
torchtyping-0.1.5.dist-info/RECORD
