Metadata-Version: 2.1
Name: torchtyping
Version: 0.1.5
Summary: Runtime type annotations for the shape, dtype etc. of PyTorch Tensors. 
Home-page: https://github.com/patrick-kidger/torchtyping
Author: Patrick Kidger
Author-email: contact@kidger.site
Maintainer: Patrick Kidger
Maintainer-email: contact@kidger.site
License: Apache-2.0
Classifier: Development Status :: 3 - Alpha
Classifier: Intended Audience :: Developers
Classifier: Intended Audience :: Financial and Insurance Industry
Classifier: Intended Audience :: Information Technology
Classifier: Intended Audience :: Science/Research
Classifier: License :: OSI Approved :: Apache Software License
Classifier: Natural Language :: English
Classifier: Programming Language :: Python :: 3
Classifier: Programming Language :: Python :: 3.7
Classifier: Programming Language :: Python :: 3.8
Classifier: Programming Language :: Python :: 3.9
Classifier: Programming Language :: Python :: Implementation :: CPython
Classifier: Topic :: Scientific/Engineering :: Artificial Intelligence
Classifier: Topic :: Scientific/Engineering :: Information Analysis
Classifier: Topic :: Scientific/Engineering :: Mathematics
Classifier: Framework :: Pytest
Requires-Python: >=3.7.0
License-File: LICENSE
Requires-Dist: torch >=1.7.0
Requires-Dist: typeguard <3,>=2.11.1
